[
    {
        "list_id":1,
        "name":"Apple",
        "image":"https://i.ibb.co/3zw3k9c/apple.jpg",
        "product_Id":101,
        "qty": "",
        "price":"124"
    },
    {
        "list_id":2,
        "name":"Orange",
        "image":"https://i.ibb.co/vvPkqj5/orange.jpg",
        "product_Id":101,
        "qty": "",
        "price":"109"
    },
    {
        "list_id":3,
        "name":"Banana",
        "image":"https://i.ibb.co/jLgrP6T/banana.jpg",
        "product_Id":101,
        "qty": "",
        "price":""
    },
    {
        "list_id":4,
        "name":"Grapes",
        "image":"https://i.ibb.co/GMBFBxb/grapes.jpg",
        "product_Id":101,
        "qty": "47",
        "price":""
    },
    {
        "list_id":5,
        "name":"Pomegranate",
        "image":"https://i.ibb.co/ByZBxk8/pomegranate.jpg",
        "product_Id":101,
        "qty": "",
        "price":"183"
    },
    {
        "list_id":6,
        "name":"Watermelon",
        "image":"https://i.ibb.co/1J1LKRm/Watermelon.jpg",
        "product_Id":101,
        "qty": "",
        "price":"57"
    },
    {
        "list_id":7,
        "name":"Pear",
        "image":"https://i.ibb.co/fx86RYn/pear.jpg",
        "product_Id":101,
        "qty": "",
        "price":"129"
    },
    {
        "list_id":8,
        "name":"Coconut",
        "image":"https://i.ibb.co/s3fBMqH/coconut.jpg",
        "product_Id":101,
        "qty": "",
        "price":"37"
    },
    {
        "list_id":9,
        "name":"Guava",
        "image_url":"https://i.ibb.co/PtQ6dWf/guava.jpg",
        "product_Id":101,
        "qty": "",
        "price":"74"
    },
    {
        "list_id":10,
        "name":"Pineapple",
        "image_url":"https://i.ibb.co/fp76q7b/pineapple.jpg",
        "product_Id":101,
        "qty": "",
        "price":"104"
    },
    {
        "list_id":11,
        "name":"Mosambi",
        "image_url":"https://i.ibb.co/KGWLB3D/mosumbi.png",
        "product_Id":101,
        "qty": "",
        "price":"92"
    },
    {
        "list_id":12,
        "name":"Musk Melon",
        "image_url":"https://i.ibb.co/DDHqjMN/muskmelon.jpg",
        "product_Id":101,
        "qty": "",
        "price":"44"
    },
    {
        "list_id":13,
        "name":"Onion",
        "image_url":"https://i.ibb.co/q9KrXd8/onion.jpg",
        "product_Id":102,
        "qty": "",
        "price":"27"
    },
    {
        "list_id":14,
        "name":"Tomato",
        "image_url":"https://i.ibb.co/q9KrXd8/onion.jpg",
        "product_Id":102,
        "qty": "",
        "price":"29"
    },
    {
        "list_id":15,
        "name":"Potato",
        "image_url":"https://i.ibb.co/Y0T5sk2/potato.jpg",
        "product_Id":102,
        "qty": "",
        "price":"24"
    },
    {
        "list_id":16,
        "name":"Cauliflower",
        "image_url":"https://i.ibb.co/82j9fh0/flower.jpg",
        "product_Id":102,
        "qty": "22",
        "price":""
    },
    {
        "list_id":17,
        "name":"Green Peas",
        "image_url":"https://i.ibb.co/TcPrpKM/green-peas.jpg",
        "product_Id":102,
        "qty": "",
        "price":"55"
    },
    {
        "list_id":18,
        "name":"Lady Finger",
        "image_url":"https://i.ibb.co/Tq3G7nm/lady-finger.jpg",
        "product_Id":102,
        "qty": "",
        "price":"44"
    },
    {
        "list_id":19,
        "name":"Garlic",
        "image_url":"https://i.ibb.co/tzLcKkY/garlic.jpg",
        "product_Id":102,
        "qty": "",
        "price":"50"
    },
    {
        "list_id":20,
        "name":"Lemon",
        "image_url":"https://i.ibb.co/B3b1Jv5/lemon.jpg",
        "product_Id":102,
        "qty": "",
        "price":"47"
    },
    {
        "list_id":21,
        "name":"Capsicum",
        "image_url":"https://i.ibb.co/gWchhSr/capsicum.jpg",
        "product_Id":102,
        "qty": "",
        "price":"74"
    },
    {
        "list_id":22,
        "name":"Cabbage",
        "image_url":"https://i.ibb.co/4F4Jdv5/cabbage.jpg",
        "product_Id":102,
        "qty": "",
        "price":"20"
    },
    {
        "list_id":23,
        "name":"Brinjal",
        "image_url":"https://i.ibb.co/wh1C6BK/brinjal.jpg",
        "product_Id":102,
        "qty": "",
        "price":"25"
    },
    {
        "list_id":24,
        "name":"Chilli",
        "image_url":"https://i.ibb.co/cQ4MDxT/chilli.jpg",
        "product_Id":102,
        "qty": "",
        "price":"25"
    },
    {
        "list_id":25,
        "name":"Idli Rice",
        "image":"https://i.ibb.co/3zw3k9c/apple.jpg",
        "product_Id":103,
        "qty": "",
        "price":"124"
    },
    {
        "list_id":26,
        "name":"Dosa Rice",
        "image":"https://i.ibb.co/vvPkqj5/orange.jpg",
        "product_Id":103,
        "qty": "",
        "price":"109"
    },
    {
        "list_id":27,
        "name":"Poha",
        "image":"https://i.ibb.co/jLgrP6T/banana.jpg",
        "product_Id":103,
        "qty": "",
        "price":""
    },
    {
        "list_id":28,
        "name":"Basmati Rice",
        "image":"https://i.ibb.co/GMBFBxb/grapes.jpg",
        "product_Id":103,
        "qty": "47",
        "price":""
    },
    {
        "list_id":29,
        "name":"Wheat Whole",
        "image":"https://i.ibb.co/ByZBxk8/pomegranate.jpg",
        "product_Id":103,
        "qty": "",
        "price":"183"
    },
    {
        "list_id":30,
        "name":"Puffed Rice",
        "image":"https://i.ibb.co/1J1LKRm/Watermelon.jpg",
        "product_Id":103,
        "qty": "",
        "price":"57"
    },
    {
        "list_id":31,
        "name":"Masoor Dal",
        "image":"https://i.ibb.co/fx86RYn/pear.jpg",
        "product_Id":104,
        "qty": "",
        "price":"129"
    },
    {
        "list_id":32,
        "name":"Urad Whole",
        "image":"https://i.ibb.co/s3fBMqH/coconut.jpg",
        "product_Id":104,
        "qty": "",
        "price":"37"
    },
    {
        "list_id":33,
        "name":"Moong Dal",
        "image_url":"https://i.ibb.co/PtQ6dWf/guava.jpg",
        "product_Id":104,
        "qty": "",
        "price":"74"
    },
    {
        "list_id":34,
        "name":"Toor Dal",
        "image":"https://i.ibb.co/fx86RYn/pear.jpg",
        "product_Id":104,
        "qty": "",
        "price":"129"
    },
    {
        "list_id":35,
        "name":"Channa Dal",
        "image":"https://i.ibb.co/s3fBMqH/coconut.jpg",
        "product_Id":104,
        "qty": "",
        "price":"37"
    },
    {
        "list_id":36,
        "name":"Peanuts",
        "image_url":"https://i.ibb.co/PtQ6dWf/guava.jpg",
        "product_Id":104,
        "qty": "",
        "price":"74"
    }
]